grandmaster/Code.py
grandmaster/Example.py
grandmaster/Input.py
grandmaster/Model.py
grandmaster/Task.py
grandmaster/Validator.py
grandmaster/__init__.py
grandmaster/annotations.py
grandmaster/config.py
grandmaster/examples.py
grandmaster/helper.py
grandmaster/inputs.py
grandmaster/outputs.py
grandmaster/tasks.py
grandmaster/models/__init__.py
grandmaster/models/ageitgey/predict.py
grandmaster/models/belory/predict.py
grandmaster/models/facebook/__init__.py
grandmaster/models/facebook/models.py
grandmaster/models/nickmuchi/predict.py
grandmaster/models/openai/__init__.py
grandmaster/models/openai/model.py
grandmaster/models/openai/clip/__init__.py
grandmaster/models/openai/clip/p.py
grandmaster/models/openai/clip/predict.py
grandmaster/models/openai/whisper/predict.py
grandmaster/todo/Grandmaster.py
grandmaster/todo/main.py
grandmaster/todo/mytypes.py
grandmaster/todo/setup_to_delete.py
grandmaster-0.0.5.dist-info/METADATA
grandmaster-0.0.5.dist-info/WHEEL
grandmaster-0.0.5.dist-info/top_level.txt
grandmaster-0.0.5.dist-info/RECORD
