Metadata-Version: 2.1
Name: grandmaster
Version: 0.0.5
Requires-Dist: torch (==1.13.1)
Requires-Dist: transformers (==4.27.3)
Requires-Dist: pillow (==8.4.0)
Requires-Dist: datasets (==2.10.1)
Requires-Dist: jinja2 (==3.1.2)
Requires-Dist: black (==23.1.0)
Requires-Dist: fastapi (==0.95.0)
